{
  "document": {
    "datasource": "interviewds",
"containerDatasourceId": "<string>",
    "objectType": "StateInfo",
    "id": "nebraska",
    "title": "Nebraska",
    "body": {
      "mimeType": "text/plain",
      "textContent": "Nebraska is best known for corn and prairie landscapes."
    },
"viewURL": "https://en.wikipedia.org/wiki/nebraska",
        "permissions": {
            "allowedUsers": [
                {
                    "email": "alex@glean-sandbox.com",
                    "datasourceUserId": "alex@glean-sandbox.com",
                    "name": "Jonathan"
                }
            ],
            "allowedGroups": ["<string>"],
            "allowedGroupIntersections": [{"requiredGroups": ["<string>"]}],
            
            
        },
    "owners": [
      {
        "name": "alex@glean-sandbox.com",
        "datasourceUserId": "alex@glean-sandbox.com"
      }
    ]
  }
}