{
  "document": {
    "datasource": "interviewds",
"containerDatasourceId": "<string>",
    "objectType": "StateInfo",
    "id": "west_virginia",
    "title": "West Virginia",
    "body": {
      "mimeType": "text/plain",
      "textContent": "West Virginia is best known for Appalachian mountains and coal mining."
    },
"viewURL": "https://en.wikipedia.org/wiki/",
        "permissions": {
            "allowedUsers": [
                {
                    "email": "alex@glean-sandbox.com",
                    "datasourceUserId": "alex@glean-sandbox.com",
                    "name": "Jonathan"
                }
            ],
            "allowedGroups": ["<string>"],
            "allowedGroupIntersections": [{"requiredGroups": ["<string>"]}],
            "allowAnonymousAccess": true,
            "allowAllDatasourceUsersAccess": true
        },
    "owners": [
      {
        "name": "jonfromnashville@gmail.com",
        "datasourceUserId": "jonfromnashville@gmail.com"
      }
    ]
  }
}